battle/__init__.py
battle/battle_content.py
tibia-battle/__init__.py
tibia-battle/battle_content.py
tibia_battle-0.0.4.dist-info/LICENSE
tibia_battle-0.0.4.dist-info/METADATA
tibia_battle-0.0.4.dist-info/WHEEL
tibia_battle-0.0.4.dist-info/top_level.txt
tibia_battle-0.0.4.dist-info/RECORD
